slug_preview/__init__.py
slug_preview/forms.py
slug_preview/models.py
slug_preview/slugify.py
slug_preview/validators.py
slug_preview/widgets.py
slug_preview/static/slug_preview/css/slug_preview.css
slug_preview/static/slug_preview/js/slug_preview.js
django_slug_preview-2.0.1.dist-info/AUTHORS
django_slug_preview-2.0.1.dist-info/LICENSE
django_slug_preview-2.0.1.dist-info/METADATA
django_slug_preview-2.0.1.dist-info/WHEEL
django_slug_preview-2.0.1.dist-info/top_level.txt
django_slug_preview-2.0.1.dist-info/RECORD
